odoo/addons/sale_quotation_number/README.rst
odoo/addons/sale_quotation_number/__init__.py
odoo/addons/sale_quotation_number/__manifest__.py
odoo/addons/sale_quotation_number/data/data.xml
odoo/addons/sale_quotation_number/i18n/ca.po
odoo/addons/sale_quotation_number/i18n/de.po
odoo/addons/sale_quotation_number/i18n/es.po
odoo/addons/sale_quotation_number/i18n/es_ES.po
odoo/addons/sale_quotation_number/i18n/fi.po
odoo/addons/sale_quotation_number/i18n/fr.po
odoo/addons/sale_quotation_number/i18n/hr.po
odoo/addons/sale_quotation_number/i18n/hu.po
odoo/addons/sale_quotation_number/i18n/it.po
odoo/addons/sale_quotation_number/i18n/nl.po
odoo/addons/sale_quotation_number/i18n/nl_NL.po
odoo/addons/sale_quotation_number/i18n/pt_BR.po
odoo/addons/sale_quotation_number/i18n/ro.po
odoo/addons/sale_quotation_number/i18n/sale_quotation_number.pot
odoo/addons/sale_quotation_number/i18n/sk.po
odoo/addons/sale_quotation_number/i18n/sl.po
odoo/addons/sale_quotation_number/i18n/tr.po
odoo/addons/sale_quotation_number/i18n/tr_TR.po
odoo/addons/sale_quotation_number/i18n/zh_CN.po
odoo/addons/sale_quotation_number/models/__init__.py
odoo/addons/sale_quotation_number/models/sale_order.py
odoo/addons/sale_quotation_number/static/description/icon.png
odoo/addons/sale_quotation_number/tests/__init__.py
odoo/addons/sale_quotation_number/tests/test_sale_order.py
odoo/addons/sale_quotation_number/views/sales_config.xml
odoo11_addon_sale_quotation_number-11.0.1.1.1.dist-info/METADATA
odoo11_addon_sale_quotation_number-11.0.1.1.1.dist-info/WHEEL
odoo11_addon_sale_quotation_number-11.0.1.1.1.dist-info/top_level.txt
odoo11_addon_sale_quotation_number-11.0.1.1.1.dist-info/RECORD
